{
  "version": 1,
  "rawExportKey": "BCH_ServOfMiori_AD",
  "completeBadge": {
    "enabled": true,
    "mainText": "COMPLETE!",
    "mainTextByLanguage": {
      "ja": "COMPLETE!",
      "en": "COMPLETE!"
    },
    "subTextTemplate": "{count} / {total} COLLECTED",
    "subTextTemplateByLanguage": {
      "ja": "{count} / {total} 集めた",
      "en": "{count} / {total} COLLECTED"
    }
  },
  "metaOverlay": {
    "showDate": true,
    "showCount": true,
    "showName": true
  },
  "text": {
    "collectedLabel": {
      "ja": "集めた",
      "en": "collected"
    }
  }
}
